test_vimdecrypt.py
vimdecrypt.py
vim_decrypt-2.0.0.dist-info/LICENSE
vim_decrypt-2.0.0.dist-info/METADATA
vim_decrypt-2.0.0.dist-info/WHEEL
vim_decrypt-2.0.0.dist-info/entry_points.txt
vim_decrypt-2.0.0.dist-info/top_level.txt
vim_decrypt-2.0.0.dist-info/RECORD
