Metadata-Version: 2.1
Name: vim-decrypt
Version: 2.0.0
Summary: Command line tool for decrypting vim-blowfish-encrypted files.
Author: Gertjan van Zwieten
Maintainer-email: Tundish <tundish@gigeconomy.org.uk>
License: GNU GENERAL PUBLIC LICENSE
Keywords: vim,blowfish,decrypt,encryption
Classifier: Programming Language :: Python
Requires-Python: >=3.8
License-File: LICENSE
Requires-Dist: blowfish (>=0.6.1)
